LFSR/Vhdl/LSFR.vhd
library ieee;
use ieee.std_logic_1164.all;

entity LSFR is
    port (
        clk : in std_logic;
        rst : in std_logic;
        lfsr_o : out std_logic_vector(2 downto 0)
    );
end LSFR;

architecture Behavioral of LSFR is
    signal lfsr_int : std_logic_vector(2 downto 0);
begin
    process(clk, rst)
    begin
        if rst = '1' then
            lfsr_int <= "000";
        elsif rising_edge(clk) then
            lfsr_int(2 downto 1) <= lfsr_int(1 downto 0);
            lfsr_int(0) <= not(lfsr_int(2) xor lfsr_int(1));
        end if;
    end process;

    lfsr_o <= lfsr_int;
end Behavioral;

LFSR/Vhdl/LSFR_TB.vhd
library ieee;
use ieee.std_logic_1164.all;
use ieee.numeric_std.all;

entity LSFR_TB is
end LSFR_TB;

architecture Behavioral of LSFR_TB is
    signal clk : std_logic := '1';
    signal rst : std_logic := '1';
    signal lfsr_o : std_logic_vector(2 downto 0);

    component LSFR is
        port (
            clk : in std_logic;
            rst : in std_logic;
            lfsr_o : out std_logic_vector(2 downto 0)
        );
    end component;

begin
    lfsr_inst: LSFR port map (
        clk => clk,
        rst => rst,
        lfsr_o => lfsr_o
    );

    clk_process : process
    begin
        wait for 5 ns;
        clk <= not clk;
    end process;

    stimulus : process
    begin
        wait for 50 ns;
        rst <= '0';
        wait for 50 ns;
        rst <= '0';
        wait for 50 ns;
        rst <= '1';
        wait for 100 ns;
		report "LSFR_TB_VHD";
        wait;
		
    end process;
end Behavioral;

LFSR/Vhdl/LSFR.vcd
$date
  Sat Jun 01 21:33:23 2024
$end
$version
  GHDL v0
$end
$timescale
  1 fs
$end
$scope module standard $end
$upscope $end
$scope module std_logic_1164 $end
$upscope $end
$scope module numeric_std $end
$upscope $end
$scope module lsfr_tb $end
$var reg 1 ! clk $end
$var reg 1 " rst $end
$var reg 3 # lfsr_o[2:0] $end
$scope module lfsr_inst $end
$var reg 1 $ clk $end
$var reg 1 % rst $end
$var reg 3 & lfsr_o[2:0] $end
$var reg 3 ' lfsr_int[2:0] $end
$upscope $end
$upscope $end
$enddefinitions $end
#0
1!
1"
b000 #
1$
1%
b000 &
b000 '
#5000000
0!
0$
#10000000
1!
1$
#15000000
0!
0$
#20000000
1!
1$
#25000000
0!
0$
#30000000
1!
1$
#35000000
0!
0$
#40000000
1!
1$
#45000000
0!
0$
#50000000
1!
0"
b001 #
1$
0%
b001 &
b001 '
#55000000
0!
0$
#60000000
1!
b011 #
1$
b011 &
b011 '
#65000000
0!
0$
#70000000
1!
b110 #
1$
b110 &
b110 '
#75000000
0!
0$
#80000000
1!
b101 #
1$
b101 &
b101 '
#85000000
0!
0$
#90000000
1!
b010 #
1$
b010 &
b010 '
#95000000
0!
0$
#100000000
1!
b100 #
1$
b100 &
b100 '
#105000000
0!
0$
#110000000
1!
b000 #
1$
b000 &
b000 '
#115000000
0!
0$
#120000000
1!
b001 #
1$
b001 &
b001 '
#125000000
0!
0$
#130000000
1!
b011 #
1$
b011 &
b011 '
#135000000
0!
0$
#140000000
1!
b110 #
1$
b110 &
b110 '
#145000000
0!
0$
#150000000
1!
1"
b000 #
1$
1%
b000 &
b000 '
