SumadorVHDL/sumador.vhdl
library ieee;
use ieee.std_logic_1164.all;

entity sumador is
    port (
        a    : in  std_logic;
        b    : in  std_logic;
        cin  : in  std_logic;
        sum  : out std_logic;
        cout : out std_logic
    );
end entity sumador;

architecture behavioral of sumador is
begin
    sum <= a xor b xor cin;
    cout <= (a and b) or (cin and (a xor b));
end architecture behavioral;

SumadorVHDL/sumador_4bits.vhdl
library ieee;
use ieee.std_logic_1164.all;

entity sumador4bits is
    port (
        a     : in  std_logic_vector(3 downto 0);
        b     : in  std_logic_vector(3 downto 0);
        cin   : in  std_logic;
        sum   : out std_logic_vector(3 downto 0);
        cout  : out std_logic
    );
end entity sumador4bits;

architecture behavioral of sumador4bits is
    signal c   : std_logic_vector(3 downto 0);
    signal s   : std_logic_vector(3 downto 0);
begin
    -- Instancias de sumador de 1 bit
    sumador_bit0 : entity work.sumador port map(a(0), b(0), cin, s(0), c(0));
    sumador_bit1 : entity work.sumador port map(a(1), b(1), c(0), s(1), c(1));
    sumador_bit2 : entity work.sumador port map(a(2), b(2), c(1), s(2), c(2));
    sumador_bit3 : entity work.sumador port map(a(3), b(3), c(2), s(3), c(3));

    -- Salidas
    sum <= s;
    cout <= c(3);
end architecture behavioral;

SumadorVHDL/sumador_4bits_tb.vhdl

library ieee;
use ieee.std_logic_1164.all;
use ieee.numeric_std.all;

entity sumador4bits_tb is end;

architecture bench of sumador4bits_tb is
  signal a : std_logic_vector(3 downto 0);
  signal b : std_logic_vector(3 downto 0);
  signal cin : std_logic;
  signal sum : std_logic_vector(3 downto 0);
  signal cout : std_logic;
begin

  sumador4bits_inst : entity work.sumador4bits
  port map (
    a => a,
    b => b,
    cin => cin,
    sum => sum,
    cout => cout
  );
-- clk <= not clk after clk_period/2;
process
begin
  -- Test case 1
  a    <= "0000";
  b    <= "0000";
  cin  <= '0';
  wait for 10 ns;
  -- Test case 2
  a    <= "1111";
  b    <= "0000";
  cin  <= '1';
  wait for 10 ns;
  -- Test case 3
  a    <= "0011";
  b    <= "1100";
  cin  <= '1';
  wait for 10 ns;
  -- Test case 4
  a    <= "0001";
  b    <= "0001";
  cin  <= '0';
  wait for 10 ns;
  -- Test case 5
  a    <= "0101";
  b    <= "1010";
  cin  <= '0';
  wait for 10 ns;
  -- Test case 6
  a    <= "1001";
  b    <= "0110";
  cin  <= '1';
  wait for 10 ns;
  -- Test case 7
  a    <= "1100";
  b    <= "0011";
  cin  <= '0';
  wait for 10 ns;
  -- Test case 8
  a    <= "1111";
  b    <= "1111";
  cin  <= '1';
  wait for 10 ns;
  -- Add more test cases as needed
  
  wait;
end process;

end;

SumadorVHDL/senales.vcd
$date
  Tue Mar 19 10:24:35 2024
$end
$version
  GHDL v0
$end
$timescale
  1 fs
$end
$scope module standard $end
$upscope $end
$scope module std_logic_1164 $end
$upscope $end
$scope module numeric_std $end
$upscope $end
$scope module sumador4bits_tb $end
$var reg 4 ! a[3:0] $end
$var reg 4 " b[3:0] $end
$var reg 1 # cin $end
$var reg 4 $ sum[3:0] $end
$var reg 1 % cout $end
$scope module sumador4bits_inst $end
$var reg 4 & a[3:0] $end
$var reg 4 ' b[3:0] $end
$var reg 1 ( cin $end
$var reg 4 ) sum[3:0] $end
$var reg 1 * cout $end
$var reg 4 + c[3:0] $end
$var reg 4 , s[3:0] $end
$scope module sumador_bit0 $end
$var reg 1 - a $end
$var reg 1 . b $end
$var reg 1 / cin $end
$var reg 1 0 sum $end
$var reg 1 1 cout $end
$upscope $end
$scope module sumador_bit1 $end
$var reg 1 2 a $end
$var reg 1 3 b $end
$var reg 1 4 cin $end
$var reg 1 5 sum $end
$var reg 1 6 cout $end
$upscope $end
$scope module sumador_bit2 $end
$var reg 1 7 a $end
$var reg 1 8 b $end
$var reg 1 9 cin $end
$var reg 1 : sum $end
$var reg 1 ; cout $end
$upscope $end
$scope module sumador_bit3 $end
$var reg 1 < a $end
$var reg 1 = b $end
$var reg 1 > cin $end
$var reg 1 ? sum $end
$var reg 1 @ cout $end
$upscope $end
$upscope $end
$upscope $end
$enddefinitions $end
#0
b0000 !
b0000 "
0#
b0000 $
0%
b0000 &
b0000 '
0(
b0000 )
0*
b0000 +
b0000 ,
0-
0.
0/
00
01
02
03
04
05
06
07
08
09
0:
0;
0<
0=
0>
0?
0@
#10000000
b1111 !
1#
b0000 $
1%
b1111 &
1(
b0000 )
1*
b1111 +
b0000 ,
1-
1/
11
12
14
05
16
17
19
0:
1;
1<
1>
0?
1@
#20000000
b0011 !
b1100 "
b0011 &
b1100 '
07
18
0<
1=
#30000000
b0001 !
b0001 "
0#
b0010 $
0%
b0001 &
b0001 '
0(
b0010 )
0*
b0001 +
b0010 ,
1.
0/
02
15
06
08
09
0:
0;
0=
0>
0?
0@
#40000000
b0101 !
b1010 "
b1111 $
0%
b0101 &
b1010 '
b1111 )
0*
b0000 +
b1111 ,
0.
10
01
13
04
15
06
17
09
1:
0;
1=
0>
1?
0@
#50000000
b1001 !
b0110 "
1#
b0000 $
1%
b1001 &
b0110 '
1(
b0000 )
1*
b1111 +
b0000 ,
1/
00
11
14
05
16
07
18
19
0:
1;
1<
0=
1>
0?
1@
#60000000
b1100 !
b0011 "
0#
b1111 $
0%
b1100 &
b0011 '
0(
b1111 )
0*
b0000 +
b1111 ,
0-
1.
0/
10
01
04
15
06
17
08
09
1:
0;
0>
1?
0@
#70000000
b1111 !
b1111 "
1#
b1111 $
1%
b1111 &
b1111 '
1(
b1111 )
1*
b1111 +
b1111 ,
1-
1/
11
12
14
15
16
18
19
1:
1;
1=
1>
1?
1@
